.gitignore
CHANGES.txt
LICENSE.txt
MANIFEST.in
README.rst
setup.py
js/__init__.py
js/__init__.pyc
js.jqueryui_tagit.egg-info/PKG-INFO
js.jqueryui_tagit.egg-info/SOURCES.txt
js.jqueryui_tagit.egg-info/dependency_links.txt
js.jqueryui_tagit.egg-info/entry_points.txt
js.jqueryui_tagit.egg-info/namespace_packages.txt
js.jqueryui_tagit.egg-info/not-zip-safe
js.jqueryui_tagit.egg-info/requires.txt
js.jqueryui_tagit.egg-info/top_level.txt
js/jqueryui_tagit/__init__.py
js/jqueryui_tagit/__init__.pyc
js/jqueryui_tagit/test_tagit.txt
js/jqueryui_tagit/resources/jquery.tagit.css
js/jqueryui_tagit/resources/jquery.tagit.min.css
js/jqueryui_tagit/resources/tag-it.js
js/jqueryui_tagit/resources/tag-it.min.js