Metadata-Version: 1.0
Name: js.jqueryui-tagit
Version: 2.0.24-2
Summary: Fanstatic packaging of Tag-it!
Home-page: https://github.com/disko/js.jqueryui_tagit
Author: Andreas Kaiser
Author-email: disko@binary-punks.com
License: BSD
Platform: UNKNOWN
